Workbook

Sheet Deshbord
A1: VANSHIDHAR PETROLEUM - HPCL PANSA
A2: Date : 14-Sep-2026
A3: Financial Metric / Indicator | B3: Amount Value (INR)
A4: Total Sales | B4: =+'Nozzle Sales Logs'!F64 -> 1002466.5
A5: Total Purchase | B5: =+'Oil Purchage'!F14 -> 2638253.2
A6: Account Balance (SBI CC) | B6: =+'SBI CC Bank Ledger'!F45 -> 738194.84
A7: Total Expense | B7: =+'Pump Miscellaneous Costs'!D19 -> 8510
A8: Total Staff Payment | B8: =+'Staff Wages Ledger'!D27 -> 28190
A9: Total Debit Interest | B9: =+'Debit Interest Book'!D18 -> 35852
A10: Owner Debit (Ashwini Kumar Singh) | B10: =+'Owner Personal Book'!E45 -> 69791
A11: Other Party Debit Summary | B11: =+'Party Credit Accounts'!E61 -> 438103
A12: HPCL Credit Balance | B12: =+'HPCL '!F17 -> 25007.23
A13: Total Oil Stock Value | B13: =+'Fuel Stock Ledger'!F40 -> 1715758.6
A14: Total Kharch & Stock Combined | B14: =+B13+B12+B11+B10+B9+B8+B7+B6 -> 3059406.6
A15: Account Credit Total | B15: =3000000+918000+400000 -> 4318000
A16: Total Debit Account Summary | B16: 1300000
A17: Balance Account Framework | B17: =+B15-B16 -> 3018000
A18: Net Operational Profit / Loss | B18: =+B14-B17 -> 41406.643

Sheet Fuel Stock Ledger
A1: VANSHIDHAR PETROLEUM - HPCL PANSA (FUEL STOCK LEDGER)
A2: Date | B2: MS Opening | C2: MS Purchase | D2: MS Sale | E2: MS Closing | F2: Stock Value | G2: HSD Opening | H2: HSD Purchase | I2: HSD Sale | J2: HSD Closing | K2: Stock Value | L2: Status
A3: 2026-08-26 | B3: 1141 | C3: 5000 | D3: 0 | E3: 6141 | F3: =+E3*107.1 -> 657701.1 | G3: 1177 | H3: 9000 | I3: 0 | J3: 10177 | K3: =+J3*102.17 -> 1039784.1 | L3: Open
A4: 2026-08-27 | B4: 6141 | C4: 0 | D4: 682.34 | E4: 5458.66 | F4: =+E4*107.1 -> 584622.49 | G4: 10177 | H4: 0 | I4: 714.43 | J4: 9462.57 | K4: =+J4*102.17 -> 966790.78 | L4: Open
A5: 2026-08-28 | B5: 5458.66 | C5: 0 | D5: 674.47 | E5: 4784.19 | F5: =+E5*107.1 -> 512386.75 | G5: 9462.57 | H5: 0 | I5: 40.71 | J5: 9421.86 | K5: =+J5*102.17 -> 962631.44 | L5: Open
A6: 2026-08-29 | B6: 4784.19 | C6: 0 | D6: 298 | E6: 4486.19 | F6: =+E6*107.1 -> 480470.95 | G6: 9421.86 | H6: 0 | I6: 13 | J6: 9408.86 | K6: =+J6*102.17 -> 961303.23 | L6: Open
A7: 2026-08-30 | B7: 4486.19 | C7: 0 | D7: 325.92 | E7: 4160.27 | F7: =+E7*107.1 -> 445564.92 | G7: 9408.86 | H7: 0 | I7: 68.83 | J7: 9340.03 | K7: =+J7*102.17 -> 954270.87 | L7: Open
A8: 2026-08-31 | B8: 4160.27 | C8: 0 | D8: 432.86 | E8: 3727.41 | F8: =+E8*107.1 -> 399205.61 | G8: 9340.03 | H8: 0 | I8: 927.33 | J8: 8412.7 | K8: =+J8*102.17 -> 859525.56 | L8: Open
A9: 2026-09-01 | B9: 3727.41 | C9: 0 | D9: 163.58 | E9: 3563.83 | F9: =+E9*107.1 -> 381686.19 | G9: 8412.7 | H9: 0 | I9: 10.93 | J9: 8401.77 | K9: =+J9*102.17 -> 858408.84 | L9: Open
A10: 2026-09-02 | B10: 3563.83 | C10: 0 | D10: 220.2 | E10: 3343.63 | F10: =+E10*107.1 -> 358102.77 | G10: 8401.77 | H10: 0 | I10: 12.97 | J10: 8388.8 | K10: =+J10*102.17 -> 857083.7 | L10: Open
A11: 2026-09-03 | B11: 3343.63 | C11: 0 | D11: 299.81 | E11: 3043.82 | F11: =+E11*106.92 -> 325445.23 | G11: 8388.8 | H11: 0 | I11: 158.76 | J11: 8230.04 | K11: =+J11*102.13 -> 840533.99 | L11: Open
A12: 2026-09-04 | B12: 3043.82 | C12: 0 | D12: 212 | E12: 2831.82 | F12: =+E12*106.92 -> 302778.19 | G12: 8230.04 | H12: 0 | I12: 108 | J12: 8122.04 | K12: =+J12*102.13 -> 829503.95 | L12: Open
A13: 2026-09-05 | B13: 2831.82 | C13: 0 | D13: 0 | E13: 2831.82 | F13: =+E13*106.92 -> 302778.19 | G13: 8122.04 | H13: 0 | I13: 0 | J13: 8122.04 | K13: =+J13*102.13 -> 829503.95 | L13: Close
A14: 2026-09-06 | B14: 2831.82 | C14: 0 | D14: 427.55 | E14: 2404.27 | F14: =+E14*106.92 -> 257064.55 | G14: 8122.04 | H14: 0 | I14: 167.72 | J14: 7954.32 | K14: =+J14*102.13 -> 812374.7 | L14: Open
A15: 2026-09-07 | B15: 2404.27 | C15: 0 | D15: 383.95 | E15: 2020.32 | F15: =+E15*106.92 -> 216012.61 | G15: 7954.32 | H15: 0 | I15: 58.45 | J15: 7895.87 | K15: =+J15*102.13 -> 806405.2 | L15: Open
A16: 2026-09-08 | B16: 2020.32 | C16: 0 | D16: 255.87 | E16: 1764.45 | F16: =+E16*106.92 -> 188654.99 | G16: 7895.87 | H16: 0 | I16: 82.16 | J16: 7813.71 | K16: =+J16*102.13 -> 798014.2 | L16: Open
A17: 2026-09-09 | B17: 1764.45 | C17: 8000 | D17: 313.28 | E17: 9451.17 | F17: =+E17*106.92 -> 1010519.1 | G17: 7813.71 | H17: 4000 | I17: 89.87 | J17: 11723.84 | K17: =+J17*102.13 -> 1197355.8 | L17: Open
A18: 2026-09-10 | B18: 9451.17 | C18: 0 | D18: 383.32 | E18: 9067.85 | F18: =+E18*106.92 -> 969534.52 | G18: 11723.84 | H18: 0 | I18: 197.69 | J18: 11526.15 | K18: =+J18*102.13 -> 1177165.7 | L18: Open
A19: 2026-09-11 | B19: 9067.85 | C19: 0 | D19: 337.29 | E19: 8730.56 | F19: =+E19*106.92 -> 933471.48 | G19: 11526.15 | H19: 0 | I19: 61.1 | J19: 11465.05 | K19: =+J19*102.13 -> 1170925.6 | L19: Open
A20: 2026-09-12 | B20: 8730.56 | C20: 0 | D20: 367.65 | E20: 8362.91 | F20: =+E20*106.92 -> 894162.34 | G20: 11465.05 | H20: 0 | I20: 28.49 | J20: 11436.56 | K20: =+J20*102.13 -> 1168015.9 | L20: Open
A21: 2026-09-13 | B21: 8362.91 | C21: 0 | D21: 435.28 | E21: 7927.63 | F21: =+E21*106.92 -> 847622.2 | G21: 11436.56 | H21: 0 | I21: 103.81 | J21: 11332.75 | K21: =+J21*102.13 -> 1157413.8 | L21: Open
A22: 2026-09-14 | B22: 7927.63 | C22: 0 | D22: 336.64 | E22: =+B22+C22-D22 -> 7590.99 | F22: =+E22*106.92 -> 811628.65 | G22: 11332.75 | H22: 0 | I22: 108.5 | J22: =+G22+H22-I22 -> 11224.25 | K22: =+J22*102.17 -> 1146781.6 | L22: Open
A23: 2026-09-15 | B23: =+E22 -> 7590.99 | C23: 0 | E23: =+B23+C23-D23 -> 7590.99 | F23: =+E23*106.92 -> 811628.65 | G23: =+J22 -> 11224.25 | H23: 0 | J23: =+J22 -> 11224.25 | K23: =+J23*102.17 -> 1146781.6 | L23: Open
A24: 2026-09-16
A25: 2026-09-17
A26: 2026-09-18
A27: 2026-09-19
A28: 2026-09-20
A29: 2026-09-21
A30: 2026-09-22
A31: 2026-09-23
A32: 2026-09-24
A33: 2026-09-25
A34: 2026-09-26
A35: 2026-09-27
A36: 2026-09-28
A37: Total Sum Variance | B37: 1141 | C37: =SUM(C3:C36) -> 13000 | D37: =SUM(D3:D36) -> 6550.01 | E37: =+B37+C37-D37 -> 7590.99 | G37: 1177 | H37: =SUM(H3:H36) -> 13000 | I37: =SUM(I3:I36) -> 2952.75 | J37: =+G37+H37-I37 -> 11224.25 | L37: -
C39: =+E37-B37 -> 6449.99 | H39: =+J37-G37 -> 10047.25
C40: =+C39*106.92 -> 689632.93 | F40: =+C40+H40 -> 1715758.6 | H40: =+H39*102.13 -> 1026125.6

Sheet Nozzle Sales Logs
A1: VANSHIDHAR PETROLEUM - HPCL PANSA (NOZZLE SALES LOGS)
A2: Date | B2: Product | C2: Nozzle # | D2: Rate/Ltr | E2: Quantity (Ltr) | F2: Total Amount | G2: Payment Mode | H2: Customer Type | I2: Status
A3: 2028-08-27 | B3: MS(Petrol) | C3: 3 | D3: 107.1 | E3: 682.34 | F3: 73078.61 | G3: UPI/Cash | H3: Retail | I3: Open
A4: 2028-08-27 | B4: HSD(Diesel) | C4: 3 | D4: 102.17 | E4: 714.43 | F4: 72993.31 | G4: UPI/Cash | H4: Retail | I4: Open
A5: 2028-08-28 | B5: MS(Petrol) | C5: 3 | D5: 107.1 | E5: 674.47 | F5: 72235.74 | G5: UPI/Cash | H5: Retail | I5: Open
A6: 2028-08-28 | B6: HSD(Diesel) | C6: 3 | D6: 102.17 | E6: 40.71 | F6: 4159.34 | G6: UPI/Cash | H6: Retail | I6: Open
A7: 2028-08-29 | B7: MS(Petrol) | C7: 3 | D7: 107.1 | E7: 298 | F7: 31915.8 | G7: UPI/Cash | H7: Retail | I7: Open
A8: 2028-08-29 | B8: HSD(Diesel) | C8: 3 | D8: 102.17 | E8: 13 | F8: 1328.21 | G8: UPI/Cash | H8: Retail | I8: Open
A9: 2028-08-30 | B9: MS(Petrol) | C9: 3 | D9: 107.1 | E9: 325.92 | F9: 34906.03 | G9: UPI/Cash | H9: Retail | I9: Open
A10: 2028-08-30 | B10: HSD(Diesel) | C10: 3 | D10: 102.17 | E10: 68.83 | F10: 7032.36 | G10: UPI/Cash | H10: Retail | I10: Open
A11: 2028-08-31 | B11: MS(Petrol) | C11: 3 | D11: 107.1 | E11: 432.86 | F11: 46359.31 | G11: UPI/Cash | H11: Retail | I11: Open
A12: 2028-08-31 | B12: HSD(Diesel) | C12: 3 | D12: 102.17 | E12: 927.33 | F12: 94745.31 | G12: UPI/Cash | H12: Retail | I12: Open
A13: 2026-09-01 | B13: MS(Petrol) | C13: 3 | D13: 107.1 | E13: 163.58 | F13: 17519.42 | G13: UPI/Cash | H13: Retail | I13: Open
A14: 2026-09-01 | B14: HSD(Diesel) | C14: 3 | D14: 102.17 | E14: 10.93 | F14: 1116.72 | G14: UPI/Cash | H14: Retail | I14: Open
... A37: 2026-09-13 | B37: HSD(Diesel) | C37: 0 | D37: 102.13 | E37: 103.81 | F37: 10602.12 | G37: UPI/Cash | H37: Retail | I37: Open
A38: 2026-09-14 | B38: MS(Petrol) | C38: 0 | D38: 106.92 | E38: =+'Fuel Stock Ledger'!D22 -> 336.64 | F38: =+E38*D38 -> 35993.549 | G38: UPI/Cash | H38: Retail | I38: Open
A39: 2026-09-14 | B39: HSD(Diesel) | C39: 0 | D39: 102.13 | E39: =+'Fuel Stock Ledger'!I22 -> 108.5 | F39: =+E39*D39 -> 11081.105 | G39: UPI/Cash | H39: Retail | I39: Open
A40: 2026-09-15 | B40: MS(Petrol) | C40: 0 | D40: 106.92 | F40: =+E40*D40 -> 0 | G40: UPI/Cash | H40: Retail | I40: Open
A41: 2026-09-15 | B41: HSD(Diesel) | C41: 0 | D41: 102.13 | F41: =+E41*D41 -> 0 | G41: UPI/Cash | H41: Retail | I41: Open
A64: Cumulative Total Sales | B64: - | C64: - | D64: - | E64: =SUM(E3:E63) -> 9502.76 | F64: =SUM(F3:F63) -> 1002466.5 | G64: - | H64: - | I64: -

Sheet Oil Purchage
A1: VANSHIDHAR PETROLEUM - HPCL PANSA
A2: Date | B2: Product | C2: HPCL Invoice/Challan | D2: Quantity (Ltr) | E2: Rate | F2: Amount | G2: Status
A3: 46260 | B3: MS(Petrol) | C3: 9024681788 | D3: 5000 | E3: 103.2954 | F3: 516477 | G3: Open
A4: 46260 | B4: HSD ( Diesel ) | C4: 9024681788 | D4: 9000 | E4: 99.76927 | F4: 897923.43 | G4: Open
A5: 46274 | B5: MS(Petrol) | C5: 9025011982 | D5: 8000 | E5: 103.11691 | F5: 824935.3 | G5: Open
A6: 46274 | B6: HSD ( Diesel ) | C6: 9025011982 | D6: 4000 | E6: 99.729367 | F6: 398917.47 | G6: Open
D14: =SUM(D3:D13) -> 26000 | F14: =SUM(F3:F13) -> 2638253.2

Sheet SBI CC Bank Ledger
A1: VANSHIDHAR PETROLEUM - HPCL PANSA (SBI CC BANK LEDGER)
A2: Date | B2: Bank/Account No | C2: Particular Description | D2: Credit (+) | E2: Debit (-) | F2: Balance Out | G2: Status
A3: 24-Aug-2026 | B3: State Bank Of India | C3: CC Loan Account Credit Vanshidhar | D3: 3000000 | E3: 0 | F3: 3000000 | G3: Open
A4: 24-Aug-2026 | B4: SBI/45496939063 | C4: CC Loan Se Kisi Trust Ke Name Pe Debit | D4: 0 | E4: 17700 | F4: 2982300 | G4: Open
A5: 24-Aug-2026 | B5: SBI/45496939063 | C5: Edfs Account Close Debit | D5: 0 | E5: 900000 | F5: 2082300 | G5: Open
A6: 24-Aug-2026 | B6: SBI/45496939063 | C6: Oil Purchage Hpcl Debit | D6: 0 | E6: 900000 | F6: 1182300 | G6: Open
A7: 25-Aug-2026 | B7: SBI/45496939063 | C7: CC Loan Account Debit Against Charges | D7: 0 | E7: 14160 | F7: 1168140 | G7: Open
A8: 2026-08-27 | B8: SBI/45496939063 | C8: Customer Online Payment | D8: 39745 | E8: 0 | F8: 1207885 | G8: Open
A9: 2026-08-28 | B9: SBI/45496939063 | C9: Customer Online Payment | D9: 33573 | E9: 0 | F9: 1241458 | G9: Open
A10: 2026-08-29 | B10: SBI/45496939063 | C10: Customer Online Payment | D10: 10074 | E10: 0 | F10: 1251532 | G10: Open
A11: 2026-08-30 | B11: SBI/45496939063 | C11: Customer Online Payment | D11: 13815 | E11: 0 | F11: 1265347 | G11: Open
A12: 2026-08-31 | B12: SBI/45496939063 | C12: Customer Online Payment & Intrest Debit | D12: 14082 | E12: 3992 | F12: 1275437 | G12: Open
A13: 2026-09-01 | B13: SBI/45496939063 | C13: Customer Online Payment | D13: 2974 | E13: 0 | F13: 1278411 | G13: Open
A14: 2026-09-02 | B14: SBI/45496939063 | C14: Customer Online Payment | D14: 12059.84 | E14: 0 | F14: 1290470.8 | G14: Open
... A25: 2026-09-13 | B25: SBI/45496939063 | C25: Customer Online Payment | D25: 25315 | E25: 0 | F25: 713581.84 | G25: Open
A26: 2026-09-14 | B26: SBI/45496939063 | C26: Customer Online Payment Status | D26: 24613 | E26: 0 | F26: =+F25+D26 -> 738194.84 | G26: Open
A27: 2026-09-15 | B27: SBI/45496939063 | C27: Customer Online Payment Status | F27: =+F26+D27 -> 738194.84 | G27: Open
A28: 2026-09-16
A29: 2026-09-17
A30: 2026-09-18
A31: 2026-09-19
A32: 2026-09-20
A33: 2026-09-21
A34: 2026-09-22
A35: 2026-09-23
A36: 2026-09-24
A37: 2026-09-25
A38: 2026-09-26
A39: 2026-09-27
... A44: 2026-09-32
A45: Account Balance Closing Summary | B45: - | C45: Net Accumulation | D45: =SUM(D3:D44) -> 3394046.8 | E45: =SUM(E3:E44) -> 2655852 | F45: =+D45-E45 -> 738194.84 | G45: -

Sheet Pump Miscellaneous Costs
A1: VANSHIDHAR PETROLEUM - HPCL PANSA (PUMP MISCELLANEOUS COSTS)
A2: Date | B2: Expense Account Head | C2: Particular Activity Detail | D2: Amount Cost | E2: Transaction Mode | F2: Status
A3: 2026-08-27 | B3: CC Loan Open Sbi | C3: Balance Sheet CA Certification audit fees | D3: 6000 | E3: Phone Pe Payment | F3: Open
A4: 2026-08-29 | B4: Ankit Mali | C4: Phool Mala Decor Daily Routine Cost | D4: 300 | E4: Petrol Pump Cash | F4: Open
A5: 2026-08-30 | B5: Ankit Mali | C5: Phool Mala Decor Daily Routine Cost | D5: 300 | E5: Petrol Pump Cash | F5: Open
A6: 2026-09-06 | B6: Pump Expense | C6: GVR Machine New Battery replacement 12volt | D6: 1060 | E6: Electricity / Store Cash | F6: Open
A7: 2026-09-06 | B7: Pump Expense | C7: CVT Stabilizer Repair Maintenance Control Card | D7: 850 | E7: Electricity / Store Cash | F7: Open
A19: Total Pump General Expenses | B19: - | C19: Aggregated Miscellaneous Cash Costs | D19: =SUM(D3:D18) -> 8510 | E19: - | F19: -

Sheet Staff Wages Ledger
A1: VANSHIDHAR PETROLEUM - HPCL PANSA (STAFF WAGES LEDGER)
A2: Date | B2: Staff Member Name | C2: Particular Specific Detail | D2: Payment Amount | E2: Disbursal Mode | F2: Status
A3: 2026-08-27 | B3: Dharmendra Kumar Singh | C3: Phone Pay Rakhi & Sweet Festival Gift | D3: 500 | E3: Salary Advance Mode | F3: Open
A4: 2026-08-28 | B4: Dharmendra Kumar Singh | C4: Personal Works Rakhi Gift Festive | D4: 2370 | E4: Salary Advance Mode | F4: Open
A5: 2026-08-28 | B5: Sourabh Kumar Singh | C5: Personal works advanced allocation | D5: 1900 | E5: Salary Advance Mode | F5: Open
A6: 2026-08-29 | B6: Sourabh Kumar Singh | C6: Personal works advanced allocation | D6: 2100 | E6: Salary Advance Mode | F6: Open
A7: 2026-08-29 | B7: Dharmendra Kumar Singh | C7: Personal works advance draw | D7: 1050 | E7: Salary Advance Mode | F7: Open
A8: 2026-08-30 | B8: Dharmendra Kumar Singh | C8: Personal works advance draw | D8: 210 | E8: Salary Advance Mode | F8: Open
A9: 2026-08-31 | B9: Sourabh Kumar Singh | C9: Personal works emergency cash | D9: 100 | E9: Salary Advance Mode | F9: Open
A10: 2026-09-01 | B10: Dharmendra Kumar Singh | C10: Personal works running cash allocation | D10: 5150 | E10: Salary Advance Mode | F10: Open
A11: 2026-09-04 | B11: Sourabh Kumar Singh | C11: Final Monthly Payment Aug-26 Clearance | D11: 8900 | E11: Salary Settlement Clear | F11: Open
A12: 2026-09-08 | B12: Dharmendra Kumar Singh | C12: Personal works intermediate draw | D12: 2200 | E12: Salary Advance Mode | F12: Open
A13: 2026-09-10 | B13: Dharmendra Kumar Singh | C13: Gudu Mistry repairs pump tip payment | D13: 500 | E13: Salary Advance Mode | F13: Open
A14: 2026-09-11 | B14: Dharmendra Kumar Singh | C14: Customer Phone Pe Adjustment Entry | D14: 210 | E14: Salary Advance Mode | F14: Open
A15: 2026-09-13 | B15: Dharmendra Kumar Singh | C15: Personal works closing advance draw | D15: 3000 | E15: Salary Advance Mode | F15: Open
A27: Total Staff Wages Disbursed | B27: - | C27: Summed Operational Labor Costs | D27: =SUM(D3:D26) -> 28190 | E27: - | F27: -

Sheet Debit Interest Book
A1: VANSHIDHAR PETROLEUM - HPCL PANSA (DEBIT INTEREST BOOK)
A2: Date | B2: Account/Loan Profile | C2: Interest Particular Detail | D2: Interest Amount | E2: Billing Class | F2: Status
A3: 24-Aug-2026 | B3: SBI/45496939063 | C3: CC Loan Account Opening Entry Trust | D3: 17700 | E3: Debit Charge Entry | F3: Open
A4: 25-Aug-2026 | B4: SBI/45496939063 | C4: CC Loan Account Processing Charges | D4: 14160 | E4: Debit Charge Entry | F4: Open
A5: 2026-08-31 | B5: SBI/45496939063 | C5: CC Loan Account Accumulated Interest | D5: 3992 | E5: Interest Applied | F5: Open
A18: Total Debit Interest Summary | B18: - | C18: Consolidated Cost Value | D18: =SUM(D3:D17) -> 35852 | E18: - | F18: -

Sheet Owner Personal Book
A1: VANSHIDHAR PETROLEUM - HPCL PANSA (OWNER PERSONAL BOOK)
A2: Date | B2: Owner Entity Name | C2: Particular Transaction Detail | D2: Credit Amount | E2: Debit Amount | F2: Balance Standing | G2: Status
A3: 2026-08-28 | B3: Ashwinini Kumar Singh | C3: Kumar Priyanka Singh Mobile Recharge | D3: 0 | E3: 350 | F3: -350 | G3: Open
A4: 2026-08-28 | B4: Ashwinini Kumar Singh | C4: Arun Mehta Cash Muslim Boy Copy Pen Gift | D4: 0 | E4: 2500 | F4: -2850 | G4: Open
A5: 2026-08-29 | B5: Ashwinini Kumar Singh | C5: Vivek Singh Tractore Driver | D5: 0 | E5: 2550 | F5: -5400 | G5: Open
A6: 2026-08-29 | B6: Ashwinini Kumar Singh | C6: Parsal Account Charges | D6: 0 | E6: 250 | F6: -5650 | G6: Open
A7: 2026-08-30 | B7: Ashwinini Kumar Singh | C7: Parsal Delivery Expenses | D7: 0 | E7: 1435 | F7: -7085 | G7: Open
A8: 2026-08-31 | B8: Ashwinini Kumar Singh | C8: Parsal Dto Fare Dharmveer Bus Driver | D8: 0 | E8: 50 | F8: -7135 | G8: Open
A9: 2026-09-02 | B9: Ashwinini Kumar Singh | C9: Mithi Lic Dk Pathak Policy | D9: 0 | E9: 11031 | F9: -18166 | G9: Open
A10: 2026-09-03 | B10: Ashwinini Kumar Singh | C10: Vivek Singh Tractore Payment | D10: 0 | E10: 10000 | F10: -28166 | G10: Open
A11: 2026-09-06 | B11: Ashwinini Kumar Singh | C11: Krishna Janmasthmi Chanda Festival | D11: 0 | E11: 1022 | F11: -29188 | G11: Open
A12: 2026-09-06 | B12: Ashwinini Kumar Singh | C12: Bullet Bike Petrol Pump Self | D12: 0 | E12: 150 | F12: -29338 | G12: Open
A13: 2026-09-07 | B13: Ashwinini Kumar Singh | C13: Bullet Bike Petrol Pump Self | D13: 0 | E13: 100 | F13: -29438 | G13: Open
A14: 2026-09-08 | B14: Ashwinini Kumar Singh | C14: Subham Phone Pe Rashid Block Payment | D14: 0 | E14: 750 | F14: -30188 | G14: Open
... A22: 2026-09-13 | B22: Ashwinini Kumar Singh | C22: Scorpio N Fastage Recharge Bikash Phone Pe | D22: 0 | E22: 500 | F22: -60791 | G22: Open
A23: 2026-09-14 | B23: Ashwinini Kumar Singh | C23: Parsuram Mehta July-26 Pay Tanker Opp Road | D23: 0 | E23: 9000 | F23: =-F22+E23 -> 69791 | G23: Open
A45: Total Owner Draw Balance | B45: - | C45: Net Closing Ledger | D45: =SUM(D3:D44) -> 0 | E45: =SUM(E3:E44) -> 69791 | F45: =+D45-E45 -> -69791 | G45: -

Sheet HPCL 
A1: VANSHIDHAR PETROLEUM - HPCL PANSA
A2: Date | B2: Particular | C2: Reference | D2: Credit | E2: Debit | F2: Balance | G2: Status
A3: 01-Aug-2026 | B3: Customer E Collection (ZE) MSHSD | C3: 1502081582 | D3: 918254 | F3: =+D3-E3 -> 918254 | G3: CLOSED
A4: 24-Aug-2026 | B4: Customer E Collection (ZE) MSHSD | C4: 1502438308 | D4: 900000 | F4: 924610 | G4: CLOSED
A5: 24-Aug-2026 | B5: Billing Docoment (RV) MSHSD | C5: 1102868078 | E5: 1414400 | F5: 410210 | G5: Open
A6: 46273 | B6: Customer E Collection (ZE) MSHSD | C6: 1502671120 | D6: 820000 | F6: =+F5+D6 -> 1230210 | G6: Open
A7: 46273 | B7: Billing Docoment (RV) MSHSD | C7: 1103178524 | E7: 1223852.8 | F7: =+F6-E7+18650 -> 25007.23 | G7: Open
D17: =SUM(D3:D16) -> 2638254 | E17: =SUM(E3:E16) -> 2638252.8 | F17: =+F7 -> 25007.23 | G17: Open

Sheet Party Credit Accounts
A1: VANSHIDHAR PETROLEUM - HPCL PANSA (PARTY CREDIT ACCOUNTS)
A2: Date | B2: Party/Customer Name | C2: Particular Reference Details | D2: Credit Dynamic | E2: Debit Dynamic | F2: Net Balance Matrix | G2: Status
A3: 01-Aug-2026 | B3: CHOTU SINGH | C3: Opening Base Balance Intrest 3% | D3: 375000 | E3: 0 | F3: 375000 | G3: Open
A4: 01-Aug-2026 | B4: GUDU SINGH | C4: Opening Base Balance Intrest 3% | D4: 265000 | E4: 0 | F4: 265000 | G4: Open
A5: 01-Aug-2026 | B5: J P CONST | C5: Opening Credit Claim Engine Records | D5: 45369 | E5: 0 | F5: 45369 | G5: Open
A6: 01-Aug-2026 | B6: Sonu Singh Ranideva | C6: Opening Running Outstandings Ledger | D6: 409318 | E6: 0 | F6: 409318 | G6: Open
A7: 01-Aug-2026 | B7: Chandan Kumar | C7: Opening Advanced Ledger Standings | D7: 600000 | E7: 0 | F7: 600000 | G7: Open
A8: 01-Aug-2026 | B8: Upendra Kumar Singh | C8: Bulk Party Running Credit Matrix | D8: 1950000 | E8: 0 | F8: 1950000 | G8: Open
A9: 01-Aug-2026 | B9: Rakesh Paswan | C9: Opening Small Fleet Account Tracker | D9: 92000 | E9: 0 | F9: 92000 | G9: Open
A10: 01-Aug-2026 | B10: Sharwan Singh | C10: Opening Logistics Party Ledger Account | D10: 304000 | E10: 0 | F10: 304000 | G10: Open
A11: 01-Aug-2026 | B11: Rakesh Singh Bairiya | C11: Opening Contract Balance Book | D11: 253860 | E11: 0 | F11: 253860 | G11: Open
A12: 01-Aug-2026 | B12: Fulendra Ram | C12: Opening Local Credit Book Summary | D12: 50000 | E12: 0 | F12: 50000 | G12: Open
A13: 01-Aug-2026 | B13: Shashi Kumar Singh | C13: Opening Ledger Book Setup | D13: 99000 | E13: 0 | F13: 99000 | G13: Open
A14: 01-Aug-2026 | B14: Suchun Singh | C14: Local Consumer Base Card Log | D14: 9089 | E14: 0 | F14: 9089 | G14: Open
... A47: 2026-09-13 | B47: Rajendra Singh Badiha | C47: Diesel & Petrol Combined Slip | D47: 0 | E47: 1200 | F47: 2800 | G47: Open
A61: Total Consolidated Party Book | C61: Aggregated Balances Summary | D61: =SUM(D3:D60) -> 5134272 | E61: =SUM(E3:E60) -> 438103 | F61: =SUM(F3:F60) -> 7594733 | G61: -

Sheet Mobil Lubes Log
A1: VANSHIDHAR PETROLEUM - HPCL PANSA (MOBIL LUBES LOG)
A2: Date | B2: Item Description | C2: Opening Qty | D2: Purchase Qty | E2: Sale Qty | F2: Closing Qty | G2: Amount Income | H2: Status
A3: 2026-09-04 | B3: HP Lal Ghoda 1 Ltr | C3: 2 | D3: 0 | E3: 2 | F3: 0 | G3: 400 | H3: Open Sale
A4: 2026-09-07 | B4: Tooty 40ml pouch | C4: 20 | D4: 0 | E4: 20 | F4: 0 | G4: 200 | H4: Open Sale
A5: 2026-09-09 | B5: Engine Oil Extra 1 Ltr | C5: 1 | D5: 0 | E5: 1 | F5: 0 | G5: 250 | H5: Open Sale
A6: 2026-09-10 | B6: Engine Oil Extra 1 Ltr | C6: 1 | D6: 0 | E6: 1 | F6: 0 | G6: 250 | H6: Open Sale
A7: 2026-09-10 | B7: Tooty 40ml pouch | C7: 10 | D7: 0 | E7: 10 | F7: 0 | G7: 50 | H7: Open Sale
A8: 2026-09-12 | B8: Tooty 40ml pouch | C8: 6 | D8: 0 | E8: 6 | F8: 0 | G8: 60 | H8: Open Sale
A9: 2026-09-13 | B9: Lal Ghoda 9 Ltr Golu | C9: 9 | D9: 0 | E9: 9 | F9: 0 | G9: 1800 | H9: Open Sale
A17: Total Lubricant Items Clear | B17: Oil Matrix | C17: - | D17: - | E17: - | F17: - | H17: -

Sheet Monthly 
A1: VANSHIDHAR PETROLEUM - HPCL PANSA
A2: Daily Report
A3: Date | B3: MS Sale | C3: HSD Sale | D3: Total Sale | E3: Purchase | F3: Account Balance (SBI CC) | G3: Total Expense | H3: Total Staff Payment | I3: Total Debit Interest | J3: Owner Debit (Ashwini Kumar Singh ) | K3: Other Party Debit Summary | L3: HPCL Credit Balance | M3: Total Oil Stock Value | N3: Total Kharch & Stock Combined | O3: Account Credit Total | P3: Total Debit Account Summary | Q3: Balance Account Framework | R3: Net Operational Profit / Loss | S3: Status
A4: 46235 | B4: =+'Nozzle Sales Logs'!F3+'Nozzle Sales Logs'!F5+'Nozzle Sales Logs'!F7+'Nozzle Sales Logs'!F9+'Nozzle Sales Logs'!F11 -> 258495.49 | C4: =+'Nozzle Sales Logs'!F4+'Nozzle Sales Logs'!F6+'Nozzle Sales Logs'!F8+'Nozzle Sales Logs'!F10+'Nozzle Sales Logs'!F12 -> 180258.53 | D4: =+C4+B4 -> 438754.02 | E4: =+'Oil Purchage'!F3+'Oil Purchage'!F4 -> 1414400.4 | F4: =+'SBI CC Bank Ledger'!F12 -> 1275437 | G4: =+'Pump Miscellaneous Costs'!D4+'Pump Miscellaneous Costs'!D5 -> 600 | H4: =+'Staff Wages Ledger'!D3+'Staff Wages Ledger'!D4+'Staff Wages Ledger'!D5+'Staff Wages Ledger'!D6+'Staff Wages Ledger'!D7+'Staff Wages Ledger'!D8+'Staff Wages Ledger'!D9 -> 8230 | I4: =+'Debit Interest Book'!D3+'Debit Interest Book'!D4+'Debit Interest Book'!D5 -> 35852 | J4: =+'Owner Personal Book'!E3+'Owner Personal Book'!E4+'Owner Personal Book'!E5+'Owner Personal Book'!E6+'Owner Personal Book'!E7+'Owner Personal Book'!E8 -> 7135 | K4: =+'Party Credit Accounts'!E22+'Party Credit Accounts'!E23+'Party Credit Accounts'!E24+'Party Credit Accounts'!E25+'Party Credit Accounts'!E26+'Party Credit Accounts'!E27+'Party Credit Accounts'!E28+'Party Credit Accounts'!E29+'Party Credit Accounts'!E30+'Party Credit Accounts'!E31+'Party Credit Accounts'!E32 -> 279093 | L4: =+'HPCL '!F5 -> 410210 | M4: =+'Fuel Stock Ledger'!F8+'Fuel Stock Ledger'!K8 -> 1258731.2 | N4: =+M4+L4+K4+J4+I4+H4+G4+F4 -> 3275288.2 | O4: =3000000+918000+400000 -> 4318000 | P4: 1300000 | Q4: =+O4-P4 -> 3018000 | R4: =+Q4-N4 -> -257288.17 | S4: Open
A5: 46266 | B5: =+'Nozzle Sales Logs'!F13+'Nozzle Sales Logs'!F15+'Nozzle Sales Logs'!F17+'Nozzle Sales Logs'!F19+'Nozzle Sales Logs'!F22+'Nozzle Sales Logs'!F24+'Nozzle Sales Logs'!F26+'Nozzle Sales Logs'!F28+'Nozzle Sales Logs'!F30+'Nozzle Sales Logs'!F32+'Nozzle Sales Logs'!F34+'Nozzle Sales Logs'!F36+'Nozzle Sales Logs'!F38+'Nozzle Sales Logs'!F40+'Nozzle Sales Logs'!F42+'Nozzle Sales Logs'!F44+'Nozzle Sales Logs'!F46+'Nozzle Sales Logs'!F49 -> 442335.12 | C5: =+'Nozzle Sales Logs'!F14+'Nozzle Sales Logs'!F16+'Nozzle Sales Logs'!F18+'Nozzle Sales Logs'!F20+'Nozzle Sales Logs'!F23+'Nozzle Sales Logs'!F25+'Nozzle Sales Logs'!F27+'Nozzle Sales Logs'!F29+'Nozzle Sales Logs'!F31+'Nozzle Sales Logs'!F33+'Nozzle Sales Logs'!F35+'Nozzle Sales Logs'!F37+'Nozzle Sales Logs'!F39+'Nozzle Sales Logs'!F41+'Nozzle Sales Logs'!F43 -> 121377.34 | D5: =+C5+B5 -> 563712.46 | E5: =+'Oil Purchage'!F5+'Oil Purchage'!F6 -> 1223852.8 | F5: =+'SBI CC Bank Ledger'!F45 -> 738194.84 | G5: =+'Pump Miscellaneous Costs'!D6+'Pump Miscellaneous Costs'!D7 -> 1910 | H5: =+'Staff Wages Ledger'!D10+'Staff Wages Ledger'!D11+'Staff Wages Ledger'!D12+'Staff Wages Ledger'!D13+'Staff Wages Ledger'!D14+'Staff Wages Ledger'!D15 -> 19960 | J5: =+'Owner Personal Book'!E9+'Owner Personal Book'!E10+'Owner Personal Book'!E11+'Owner Personal Book'!E12+'Owner Personal Book'!E13+'Owner Personal Book'!E14+'Owner Personal Book'!E15+'Owner Personal Book'!E16+'Owner Personal Book'!E17+'Owner Personal Book'!E18+'Owner Personal Book'!E19+'Owner Personal Book'!E20+'Owner Personal Book'!E21+'Owner Personal Book'!E22+'Owner Personal Book'!E23+'Owner Personal Book'!E24+'Owner Personal Book'!E25+'Owner Personal Book'!E26+'Owner Personal Book'!E27+'Owner Personal Book'!E28+'Owner Personal Book'!E29 -> 62656 | K5: =+'Party Credit Accounts'!E33+'Party Credit Accounts'!E34+'Party Credit Accounts'!E35+'Party Credit Accounts'!E36+'Party Credit Accounts'!E37+'Party Credit Accounts'!E38+'Party Credit Accounts'!E39+'Party Credit Accounts'!E40+'Party Credit Accounts'!E41+'Party Credit Accounts'!E42+'Party Credit Accounts'!E43+'Party Credit Accounts'!E44+'Party Credit Accounts'!E45+'Party Credit Accounts'!E46+'Party Credit Accounts'!E47+'Party Credit Accounts'!E48+'Party Credit Accounts'!E49+'Party Credit Accounts'!E50+'Party Credit Accounts'!E51+'Party Credit Accounts'!E52+'Party Credit Accounts'!E53+'Party Credit Accounts'!E54+'Party Credit Accounts'!E55+'Party Credit Accounts'!E56+'Party Credit Accounts'!E57+'Party Credit Accounts'!E58+'Party Credit Accounts'!E59 -> 159010 | L5: =+'HPCL '!F17 -> 25007.23 | S5: Open
A6: 46296 | D6: =+C6+B6 -> 0 | S6: Open
A7: 46327 | D7: =+C7+B7 -> 0 | S7: Open
A8: 46357 | D8: =+C8+B8 -> 0 | S8: Open
A9: 46388 | D9: =+C9+B9 -> 0 | S9: Open
A10: 46419 | D10: =+C10+B10 -> 0 | S10: Open
A11: 46447 | D11: =+C11+B11 -> 0 | S11: Open
A12: 46478 | D12: =+C12+B12 -> 0 | S12: Open
A13: 46508 | D13: =+C13+B13 -> 0 | S13: Close
A14: 46539 | D14: =+C14+B14 -> 0 | S14: Open
A15: 46569 | D15: =+C15+B15 -> 0 | S15: Open
A16: 46600 | D16: =+C16+B16 -> 0 | S16: Open
A17: 46631 | S17: Open
A18: 46661 | S18: Open
A19: 46692 | S19: Open
A20: 46722 | S20: Open
A21: 46753 | S21: Open
A22: 46784 | S22: Open
A23: 46813 | S23: Open
A24: 46844 | S24: Open
A25: 46874 | S25: Open
A26: 46905 | S26: Open
A27: 46935 | S27: Open
A28: 46966 | S28: Open
... A38: 47270 | S38: Open
B39: =SUM(B4:B38) -> 700830.61 | C39: =SUM(C4:C38) -> 301635.88 | D39: =SUM(D4:D38) -> 1002466.5 | E39: =SUM(E4:E38) -> 2638253.2 | F39: =SUM(F4:F38) -> 2013631.8 | G39: =SUM(G4:G38) -> 2510 | H39: =SUM(H4:H38) -> 28190 | I39: =SUM(I4:I38) -> 35852 | ... R39: =SUM(R4:R38) -> -257288.17 | S39: Open

Sheet Yearly
A1: VANSHIDHAR PETROLEUM - HPCL PANSA
A2: Yearly
A3: Date | B3: MS Sale | C3: HSD Sale | D3: Total Sale | E3: Purchase | F3: Account Balance (SBI CC) | G3: Total Expense | H3: Total Staff Payment | I3: Total Debit Interest | J3: Owner Debit (Ashwini Kumar Singh ) | K3: Other Party Debit Summary | L3: HPCL Credit Balance | M3: Total Oil Stock Value | N3: Total Kharch & Stock Combined | O3: Account Credit Total | P3: Total Debit Account Summary | Q3: Balance Account Framework | R3: Net Operational Profit / Loss | S3: Status
A4: Aug-2026 to July-2027 | S4: Open
A5: Aug-2026 to July-2028 | S5: Open
A6: Aug-2026 to July-2029 | S6: Open
A7: Aug-2026 to July-2030 | S7: Open
A8: Aug-2026 to July-2031 | S8: Open
A9: Aug-2026 to July-2032 | S9: Open
A10: Aug-2026 to July-2033 | S10: Open
A11: Aug-2026 to July-2034 | S11: Open
A12: Aug-2026 to July-2035 | S12: Open
S13: Open
